mkdocs_obsidian_bridge/__init__.py
mkdocs_obsidian_bridge/plugin.py
mkdocs_obsidian_bridge-1.3.1.dist-info/METADATA
mkdocs_obsidian_bridge-1.3.1.dist-info/WHEEL
mkdocs_obsidian_bridge-1.3.1.dist-info/entry_points.txt
mkdocs_obsidian_bridge-1.3.1.dist-info/licenses/LICENSE
mkdocs_obsidian_bridge-1.3.1.dist-info/RECORD
