Metadata-Version: 2.4
Name: mkdocs-obsidian-bridge
Version: 1.3.1
Summary: An MkDocs plugin that helps exporting your Obsidian vault as an MkDocs site.
Project-URL: Homepage, https://github.com/GooRoo/mkdocs-obsidian-bridge
Project-URL: Issues, https://github.com/GooRoo/mkdocs-obsidian-bridge/issues
Project-URL: Repository, https://github.com/GooRoo/mkdocs-obsidian-bridge.git
Author-email: GooRoo <sergey.olendarenko@gmail.com>
License-Expression: BSD-3-Clause
License-File: LICENSE
Classifier: Development Status :: 5 - Production/Stable
Classifier: Environment :: Plugins
Classifier: Framework :: MkDocs
Classifier: License :: OSI Approved :: BSD License
Classifier: Programming Language :: Python :: 3
Classifier: Programming Language :: Python :: 3.10
Classifier: Topic :: Documentation
Classifier: Topic :: Software Development :: Documentation
Classifier: Topic :: Text Processing :: Markup :: HTML
Classifier: Topic :: Text Processing :: Markup :: Markdown
Requires-Python: <4,>=3.10
Requires-Dist: markdown>=3.2.1
Requires-Dist: mkdocs>=1.4.2
Requires-Dist: obsidian-callouts>=1.0.0
Requires-Dist: obsidian-media>=2.0.0
